{
    "MINP_256_MinMax":
    {
        "label": "PixelIntNorm(MinMax); Resize(256, 256)",
        "transforms":[
            {"name": "ScaleIntensityRanged", "params":{"keys":["image"], "a_min":0, "a_max":1}, "note": "MinMax"},
            {"name": "Resized", "params":{"keys":["image", "segmentation"], "spatial_size":[256, 256], "mode":"nearest"}}
        ]
    },

    "MINP_512_MinMax":
    {
        "label": "PixelIntNorm(MinMax); Resize(512, 512)",
        "transforms":[
            {"name": "ScaleIntensityRanged", "params":{"keys":["image"], "a_min":0, "a_max":1}, "note": "MinMax"},
            {"name": "Resized", "params":{"keys":["image", "segmentation"], "spatial_size":[512, 512], "mode":"nearest"}}
        ]
    },

    "MINP_1024_MinMax":
    {
        "label": "PixelIntNorm(MinMax); Resize(1024, 1024)",
        "transforms":[
            {"name": "ScaleIntensityRanged", "params":{"keys":["image"], "a_min":0, "a_max":1}, "note": "MinMax"},
            {"name": "Resized", "params":{"keys":["image", "segmentation"], "spatial_size":[1024, 1024], "mode":"nearest"}}
        ]
    },

    "MINP_256_448_MinMax":
    {
        "label": "PixelIntNorm(MinMax); Resize(256, 448)",
        "transforms":[
            {"name": "ScaleIntensityRanged", "params":{"keys":["image"], "a_min":0, "a_max":1}, "note": "MinMax"},
            {"name": "Resized", "params":{"keys":["image", "segmentation"], "spatial_size":[256, 448], "mode":"nearest"}}
        ]
    },

    "MINP_512_896_MinMax":
    {
        "label": "PixelIntNorm(MinMax); Resize(512, 896)",
        "transforms":[
            {"name": "ScaleIntensityRanged", "params":{"keys":["image"], "a_min":0, "a_max":1}, "note": "MinMax"},
            {"name": "Resized", "params":{"keys":["image", "segmentation"], "spatial_size":[512, 896], "mode":"nearest"}}
        ]
    },

    "MINP_1024_1792_MinMax":
    {
        "label": "PixelIntNorm(MinMax); Resize(1024, 1792)",
        "transforms":[
            {"name": "ScaleIntensityRanged", "params":{"keys":["image"], "a_min":0, "a_max":1}, "note": "MinMax"},
            {"name": "Resized", "params":{"keys":["image", "segmentation"], "spatial_size":[1024, 1792], "mode":"nearest"}}
        ]
    },

    "MINP_256_P1P99":
    {
        "label": "PixelIntNorm(P1P99); Resize(256, 256)",
        "transforms":[
            {"name": "ScaleIntensityRangePercentilesd", "params":{"keys":["image"], "lower":1, "upper":99, "b_min":0, "b_max":1}, "note": "p1p99"},
            {"name": "Resized", "params":{"keys":["image", "segmentation"], "spatial_size":[256, 256], "mode":"nearest"}}
        ]
    },

    "MINP_512_P1P99":
    {
        "label": "PixelIntNorm(P1P99); Resize(512, 512)",
        "transforms":[
            {"name": "ScaleIntensityRangePercentilesd", "params":{"keys":["image"], "lower":1, "upper":99, "b_min":0, "b_max":1}, "note": "p1p99"},
            {"name": "Resized", "params":{"keys":["image", "segmentation"], "spatial_size":[512, 512], "mode":"nearest"}}
        ]
    },

    "MINP_1024_P1P99":
    {
        "label": "PixelIntNorm(P1P99); Resize(1024, 1024)",
        "transforms":[
            {"name": "ScaleIntensityRangePercentilesd", "params":{"keys":["image"], "lower":1, "upper":99, "b_min":0, "b_max":1}, "note": "p1p99"},
            {"name": "Resized", "params":{"keys":["image", "segmentation"], "spatial_size":[1024, 1024], "mode":"nearest"}}
        ]
    },

    "MINP_256_448_P1P99":
    {
        "label": "PixelIntNorm(P1P99); Resize(256, 448)",
        "transforms":[
            {"name": "ScaleIntensityRangePercentilesd", "params":{"keys":["image"], "lower":1, "upper":99, "b_min":0, "b_max":1}, "note": "p1p99"},
            {"name": "Resized", "params":{"keys":["image", "segmentation"], "spatial_size":[256, 448], "mode":"nearest"}}
        ]
    },

    "MINP_512_896_P1P99":
    {
        "label": "PixelIntNorm(P1P99); Resize(512, 896)",
        "transforms":[
            {"name": "ScaleIntensityRangePercentilesd", "params":{"keys":["image"], "lower":1, "upper":99, "b_min":0, "b_max":1}, "note": "p1p99"},
            {"name": "Resized", "params":{"keys":["image", "segmentation"], "spatial_size":[512, 896], "mode":"nearest"}}
        ]
    },

    "MINP_1024_1792_P1P99":
    {
        "label": "PixelIntNorm(P1P99); Resize(1024, 1792)",
        "transforms":[
            {"name": "ScaleIntensityRangePercentilesd", "params":{"keys":["image"], "lower":1, "upper":99, "b_min":0, "b_max":1}, "note": "p1p99"},
            {"name": "Resized", "params":{"keys":["image", "segmentation"], "spatial_size":[1024, 1792], "mode":"nearest"}}
        ]
    },

    "MINP_256_ZScore":
    {
        "label": "PixelIntNorm(ZScore); Resize(256, 256)",
        "transforms":[
            {"name": "NormalizeIntensityd", "params":{"keys":["image"], "nonzero":"True"}, "note":"ZScore"},
            {"name": "Resized", "params":{"keys":["image", "segmentation"], "spatial_size":[256, 256], "mode":"nearest"}}
        ]
    },

    "MINP_512_ZScore":
    {
        "label": "PixelIntNorm(ZScore); Resize(512, 512)",
        "transforms":[
            {"name": "NormalizeIntensityd", "params":{"keys":["image"], "nonzero":"True"}, "note":"ZScore"},
            {"name": "Resized", "params":{"keys":["image", "segmentation"], "spatial_size":[512, 512], "mode":"nearest"}}
        ]
    },

    "MINP_1024_ZScore":
    {
        "label": "PixelIntNorm(ZScore); Resize(1024, 1024)",
        "transforms":[
            {"name": "NormalizeIntensityd", "params":{"keys":["image"], "nonzero":"True"}, "note":"ZScore"},
            {"name": "Resized", "params":{"keys":["image", "segmentation"], "spatial_size":[1024, 1024], "mode":"nearest"}}
        ]
    },

    "MINP_256_448_ZScore":
    {
        "label": "PixelIntNorm(ZScore); Resize(256, 448)",
        "transforms":[
            {"name": "NormalizeIntensityd", "params":{"keys":["image"], "nonzero":"True"}, "note":"ZScore"},
            {"name": "Resized", "params":{"keys":["image", "segmentation"], "spatial_size":[256, 448], "mode":"nearest"}}
        ]
    },

    "MINP_512_896_ZScore":
    {
        "label": "PixelIntNorm(ZScore); Resize(512, 896)",
        "transforms":[
            {"name": "NormalizeIntensityd", "params":{"keys":["image"], "nonzero":"True"}, "note":"ZScore"},
            {"name": "Resized", "params":{"keys":["image", "segmentation"], "spatial_size":[512, 896], "mode":"nearest"}}
        ]
    },

    "MINP_1024_1792_ZScore":
    {
        "label": "PixelIntNorm(ZScore); Resize(1024, 1792)",
        "transforms":[
            {"name": "NormalizeIntensityd", "params":{"keys":["image"], "nonzero":"True"}, "note":"ZScore"},
            {"name": "Resized", "params":{"keys":["image", "segmentation"], "spatial_size":[1024, 1792], "mode":"nearest"}}
        ]
    },

    "MINP_256_HistNorm":
    {
        "label": "PixelIntNorm(HistNorm); Resize(256, 256)",
        "transforms":[
            {"name": "HistogramNormalized", "params":{"keys":["image"],"num_bins":500, "min":0, "max":4095}, "note": "HistNorm"},
            {"name": "Resized", "params":{"keys":["image", "segmentation"], "spatial_size":[256, 256], "mode":"nearest"}}
        ]
    },

    "MINP_512_HistNorm":
    {
        "label": "PixelIntNorm(HistNorm); Resize(512, 512)",
        "transforms":[
            {"name": "HistogramNormalized", "params":{"keys":["image"],"num_bins":500, "min":0, "max":4095}, "note": "HistNorm"},
            {"name": "Resized", "params":{"keys":["image", "segmentation"], "spatial_size":[512, 512], "mode":"nearest"}}
        ]
    },

    "MINP_1024_HistNorm":
    {
        "label": "PixelIntNorm(HistNorm); Resize(1024, 1024)",
        "transforms":[
            {"name": "HistogramNormalized", "params":{"keys":["image"],"num_bins":500, "min":0, "max":4095}, "note": "HistNorm"},
            {"name": "Resized", "params":{"keys":["image", "segmentation"], "spatial_size":[1024, 1024], "mode":"nearest"}}
        ]
    },

    "MINP_256_448_HistNorm":
    {
        "label": "PixelIntNorm(HistNorm); Resize(256, 448)",
        "transforms":[
            {"name": "HistogramNormalized", "params":{"keys":["image"],"num_bins":500, "min":0, "max":4095}, "note": "HistNorm"},
            {"name": "Resized", "params":{"keys":["image", "segmentation"], "spatial_size":[256, 448], "mode":"nearest"}}
        ]
    },

    "MINP_512_896_HistNorm":
    {
        "label": "PixelIntNorm(HistNorm); Resize(512, 896)",
        "transforms":[
            {"name": "HistogramNormalized", "params":{"keys":["image"],"num_bins":500, "min":0, "max":4095}, "note": "HistNorm"},
            {"name": "Resized", "params":{"keys":["image", "segmentation"], "spatial_size":[512, 896], "mode":"nearest"}}
        ]
    },

    "MINP_1024_1792_HistNorm":
    {
        "label": "PixelIntNorm(HistNorm); Resize(1024, 1792)",
        "transforms":[
            {"name": "HistogramNormalized", "params":{"keys":["image"],"num_bins":500, "min":0, "max":4095}, "note": "HistNorm"},
            {"name": "Resized", "params":{"keys":["image", "segmentation"], "spatial_size":[1024, 1792], "mode":"nearest"}}
        ]
    },

    "MIP_256_MinMax":
    {
        "label": "PixelSpac; PixelIntNorm(MinMax); Pad to square to max size; Resize(256, 256)",
        "transforms":[
            {"name": "Spacingd", "params": {"keys":["image", "segmentation"], "pixdim": [1.0], "mode":"nearest"}},
            {"name": "ScaleIntensityRanged", "params":{"keys":["image"], "a_min":0, "a_max":1}, "note": "MinMax"},
            {"name": "SpatialPadd", "params":{"keys":["image", "segmentation"], "spatial_size":[4084, 4084], "method":"end", "mode":"edge"}},
            {"name": "Resized", "params":{"keys":["image", "segmentation"], "spatial_size":[256, 256], "mode":"nearest"}}
        ]
    },

    "MIP_512_MinMax":
    {
        "label": "PixelSpac; PixelIntNorm(MinMax); Pad to square to max size; Resize(512, 512)",
        "transforms":[
            {"name": "Spacingd", "params": {"keys":["image", "segmentation"], "pixdim": [1.0], "mode":"nearest"}},
            {"name": "ScaleIntensityRanged", "params":{"keys":["image"], "a_min":0, "a_max":1}, "note": "MinMax"},
            {"name": "SpatialPadd", "params":{"keys":["image", "segmentation"], "spatial_size":[4084, 4084], "method":"end", "mode":"edge"}},
            {"name": "Resized", "params":{"keys":["image", "segmentation"], "spatial_size":[512, 512], "mode":"nearest"}}
        ]
    },

    "MIP_1024_MinMax":
    {
        "label": "PixelSpac; PixelIntNorm(MinMax); Pad to square to max size; Resize(1024, 1024)",
        "transforms":[
            {"name": "Spacingd", "params": {"keys":["image", "segmentation"], "pixdim": [1.0], "mode":"nearest"}},
            {"name": "ScaleIntensityRanged", "params":{"keys":["image"], "a_min":0, "a_max":1}, "note": "MinMax"},
            {"name": "SpatialPadd", "params":{"keys":["image", "segmentation"], "spatial_size":[4084, 4084], "method":"end", "mode":"edge"}},
            {"name": "Resized", "params":{"keys":["image", "segmentation"], "spatial_size":[1024, 1024], "mode":"nearest"}}
        ]
    },
    
    "MIP_256_P1P99":
    {
        "label": "PixelSpac; PixelIntNorm(P1P99); Pad to square to max size; Resize(256, 256)",
        "transforms":[
            {"name": "Spacingd", "params": {"keys":["image", "segmentation"], "pixdim": [1.0], "mode":"nearest"}},
            {"name": "ScaleIntensityRangePercentilesd", "params":{"keys":["image"], "lower":1, "upper":99, "b_min":0, "b_max":1}, "note": "p1p99"},
            {"name": "SpatialPadd", "params":{"keys":["image", "segmentation"], "spatial_size":[4084, 4084], "method":"end", "mode":"edge"}},
            {"name": "Resized", "params":{"keys":["image", "segmentation"], "spatial_size":[256, 256], "mode":"nearest"}}
        ]
    },

    "MIP_512_P1P99":
    {
        "label": "PixelSpac; PixelIntNorm(P1P99); Pad to square to max size; Resize(512, 512)",
        "transforms":[
            {"name": "Spacingd", "params": {"keys":["image", "segmentation"], "pixdim": [1.0], "mode":"nearest"}},
            {"name": "ScaleIntensityRangePercentilesd", "params":{"keys":["image"], "lower":1, "upper":99, "b_min":0, "b_max":1}, "note": "p1p99"},
            {"name": "SpatialPadd", "params":{"keys":["image", "segmentation"], "spatial_size":[4084, 4084], "method":"end", "mode":"edge"}},
            {"name": "Resized", "params":{"keys":["image", "segmentation"], "spatial_size":[512, 512], "mode":"nearest"}}
        ]
    },
    
    "MIP_1024_P1P99":
    {
        "label": "PixelSpac; PixelIntNorm(P1P99); Pad to square to max size; Resize(1024, 1024)",
        "transforms":[
            {"name": "Spacingd", "params": {"keys":["image", "segmentation"], "pixdim": [1.0], "mode":"nearest"}},
            {"name": "ScaleIntensityRangePercentilesd", "params":{"keys":["image"], "lower":1, "upper":99, "b_min":0, "b_max":1}, "note": "p1p99"},
            {"name": "SpatialPadd", "params":{"keys":["image", "segmentation"], "spatial_size":[4084, 4084], "method":"end", "mode":"edge"}},
            {"name": "Resized", "params":{"keys":["image", "segmentation"], "spatial_size":[1024, 1024], "mode":"nearest"}}
        ]
    },

    "MIP_256_ZScore":
    {
        "label": "PixelSpac; PixelIntNorm(ZScore); Pad to square to max size; Resize(256, 256)",
        "transforms":[
            {"name": "Spacingd", "params": {"keys":["image", "segmentation"], "pixdim": [1.0], "mode":"nearest"}},
            {"name": "NormalizeIntensityd", "params":{"keys":["image"], "nonzero":"True"}, "note":"ZScore"},
            {"name": "SpatialPadd", "params":{"keys":["image", "segmentation"], "spatial_size":[4084, 4084], "method":"end", "mode":"edge"}},
            {"name": "Resized", "params":{"keys":["image", "segmentation"], "spatial_size":[256, 256], "mode":"nearest"}}
        ]
    },

    "MIP_512_ZScore":
    {
        "label": "PixelSpac; PixelIntNorm(ZScore); Pad to square to max size; Resize(512, 512)",
        "transforms":[
            {"name": "Spacingd", "params": {"keys":["image", "segmentation"], "pixdim": [1.0], "mode":"nearest"}},
            {"name": "NormalizeIntensityd", "params":{"keys":["image"], "nonzero":"True"}, "note":"ZScore"},
            {"name": "SpatialPadd", "params":{"keys":["image", "segmentation"], "spatial_size":[4084, 4084], "method":"end", "mode":"edge"}},
            {"name": "Resized", "params":{"keys":["image", "segmentation"], "spatial_size":[512, 512], "mode":"nearest"}}
        ]
    },

    "MIP_1024_ZScore":
    {
        "label": "PixelSpac; PixelIntNorm(ZScore); Pad to square to max size; Resize(1024, 1024)",
        "transforms":[
            {"name": "Spacingd", "params": {"keys":["image", "segmentation"], "pixdim": [1.0], "mode":"nearest"}},
            {"name": "NormalizeIntensityd", "params":{"keys":["image"], "nonzero":"True"}, "note":"ZScore"},
            {"name": "SpatialPadd", "params":{"keys":["image", "segmentation"], "spatial_size":[4084, 4084], "method":"end", "mode":"edge"}},
            {"name": "Resized", "params":{"keys":["image", "segmentation"], "spatial_size":[1024, 1024], "mode":"nearest"}}
        ]
    },

    "MIP_256_HistNorm":
    {
        "label": "PixelSpac; PixelIntNorm(HistNorm); Pad to square to max size; Resize(256, 256)",
        "transforms":[
            {"name": "Spacingd", "params": {"keys":["image", "segmentation"], "pixdim": [1.0], "mode":"nearest"}},
            {"name": "HistogramNormalized", "params":{"keys":["image"],"num_bins":500, "min":0, "max":4095}, "note": "HistNorm"},
            {"name": "SpatialPadd", "params":{"keys":["image", "segmentation"], "spatial_size":[4084, 4084], "method":"end", "mode":"edge"}},
            {"name": "Resized", "params":{"keys":["image", "segmentation"], "spatial_size":[256, 256], "mode":"nearest"}}
        ]
    },

    "MIP_512_HistNorm":
    {
        "label": "PixelSpac; PixelIntNorm(HistNorm); Pad to square to max size; Resize(512, 512)",
        "transforms":[
            {"name": "Spacingd", "params": {"keys":["image", "segmentation"], "pixdim": [1.0], "mode":"nearest"}},
            {"name": "HistogramNormalized", "params":{"keys":["image"],"num_bins":500, "min":0, "max":4095}, "note": "HistNorm"},
            {"name": "SpatialPadd", "params":{"keys":["image", "segmentation"], "spatial_size":[4084, 4084], "method":"end", "mode":"edge"}},
            {"name": "Resized", "params":{"keys":["image", "segmentation"], "spatial_size":[512, 512], "mode":"nearest"}}
        ]
    },

    "MIP_1024_HistNorm":
    {
        "label": "PixelSpac; PixelIntNorm(HistNorm); Pad to square to max size; Resize(1024, 1024)",
        "transforms":[
            {"name": "Spacingd", "params": {"keys":["image", "segmentation"], "pixdim": [1.0], "mode":"nearest"}},
            {"name": "HistogramNormalized", "params":{"keys":["image"],"num_bins":500, "min":0, "max":4095}, "note": "HistNorm"},
            {"name": "SpatialPadd", "params":{"keys":["image", "segmentation"], "spatial_size":[4084, 4084], "method":"end", "mode":"edge"}},
            {"name": "Resized", "params":{"keys":["image", "segmentation"], "spatial_size":[1024, 1024], "mode":"nearest"}}
        ]
    }
}
